nrk_psapi/__init__.py
nrk_psapi/api.py
nrk_psapi/auth/__init__.py
nrk_psapi/auth/auth.py
nrk_psapi/auth/const.py
nrk_psapi/auth/models.py
nrk_psapi/auth/utils.py
nrk_psapi/caching.py
nrk_psapi/cli/__init__.py
nrk_psapi/cli/main.py
nrk_psapi/cli/utils.py
nrk_psapi/const.py
nrk_psapi/exceptions.py
nrk_psapi/models/__init__.py
nrk_psapi/models/catalog.py
nrk_psapi/models/channels.py
nrk_psapi/models/common.py
nrk_psapi/models/interaction.py
nrk_psapi/models/metadata.py
nrk_psapi/models/pages.py
nrk_psapi/models/playback.py
nrk_psapi/models/recommendations.py
nrk_psapi/models/rss.py
nrk_psapi/models/ruff.toml
nrk_psapi/models/search.py
nrk_psapi/models/userdata.py
nrk_psapi/py.typed
nrk_psapi/rss/__init__.py
nrk_psapi/rss/extensions.py
nrk_psapi/rss/feed.py
nrk_psapi/utils.py
nrk_psapi/version.py
nrk_psapi-0.11.2.dist-info/LICENSE.md
nrk_psapi-0.11.2.dist-info/METADATA
nrk_psapi-0.11.2.dist-info/WHEEL
nrk_psapi-0.11.2.dist-info/entry_points.txt
nrk_psapi-0.11.2.dist-info/RECORD
