Metadata-Version: 2.3
Name: nrk-psapi
Version: 0.11.2
Summary: Unofficial python library for interacting with the NRK Podcast API.
License: MIT
Keywords: podcast,api-client,unofficial
Author: Bendik R. Brenne
Author-email: bendik@konstant.no
Requires-Python: >=3.12,<4.0
Classifier: Environment :: Console
Classifier: Intended Audience :: Developers
Classifier: License :: OSI Approved :: MIT License
Classifier: Programming Language :: Python
Classifier: Programming Language :: Python :: 3
Classifier: Programming Language :: Python :: 3.12
Classifier: Programming Language :: Python :: 3.13
Provides-Extra: doc
Provides-Extra: test
Requires-Dist: aiofiles (>=24.1.0,<25.0.0)
Requires-Dist: aiohttp (>=3.10.9,<4.0.0)
Requires-Dist: async-timeout (>=4.0.3,<5.0.0)
Requires-Dist: asyncstdlib (>=3.12.5,<4.0.0)
Requires-Dist: cloudpickle (>=3.0.0,<4.0.0)
Requires-Dist: diskcache (>=5.6.3,<6.0.0)
Requires-Dist: isodate (>=0.7.2,<0.8.0)
Requires-Dist: mashumaro[orjson] (>=3.13.1,<4.0.0)
Requires-Dist: orjson (>=3.10.7,<4.0.0)
Requires-Dist: pillow (>=10.4,<12.0)
Requires-Dist: platformdirs (>=4.3.6,<5.0.0)
Requires-Dist: rfeed (>=1.1.1,<2.0.0)
Requires-Dist: rich (>=13.9.2,<14.0.0)
Requires-Dist: scrypt (>=0.8.24,<0.9.0)
Project-URL: Documentation, https://nrk-psapi.readthedocs.io/en/latest/
Project-URL: Homepage, https://github.com/bendikrb/nrk-psapi
Project-URL: Repository, https://github.com/bendikrb/nrk-psapi
